LICENSE
README.rst
setup.py
bluexpress24/handler.py
bluexpress24/settings.py
django_bluexpress_24.egg-info/PKG-INFO
django_bluexpress_24.egg-info/SOURCES.txt
django_bluexpress_24.egg-info/dependency_links.txt
django_bluexpress_24.egg-info/requires.txt
django_bluexpress_24.egg-info/top_level.txt