Metadata-Version: 2.1
Name: django-bluexpress-24
Version: 1.0.1
Summary: Django Bluexpress 24 Integration
Home-page: https://gitlab.com/linets/ecommerce/oms/integrations/oms-bluexpress/
Author: Linets Development Team
Author-email: dteam@linets.cl
License: MIT
Platform: UNKNOWN
Requires-Python: >=3.7
License-File: LICENSE
